pyroll/pyroll.py
pyroll-2.0.dist-info/LICENSE
pyroll-2.0.dist-info/METADATA
pyroll-2.0.dist-info/WHEEL
pyroll-2.0.dist-info/RECORD
